structlog_telemetry/__init__.py
structlog_telemetry/singleton_base.py
structlog_telemetry/structlog_telemetry.py
structlog_telemetry/version.py
structlog_telemetry-2.0.0.dist-info/METADATA
structlog_telemetry-2.0.0.dist-info/WHEEL
structlog_telemetry-2.0.0.dist-info/licenses/LICENSE
structlog_telemetry-2.0.0.dist-info/RECORD
