Metadata-Version: 2.3
Name: structlog_telemetry
Version: 2.0.0
Summary: A Structured Logger For Telemetry
Project-URL: Homepage, https://github.com/cyber-francis/structlog_telemetry
Project-URL: Issues, https://github.com/cyber-francis/structlog_telemetry/issues
Author-email: Francis Obiagwu <cyber.francis@comcast.net>
License-File: LICENSE
Keywords: log,logging,observability,structlog,telemetry
Classifier: License :: OSI Approved :: MIT License
Classifier: Operating System :: OS Independent
Classifier: Programming Language :: Python :: 3
Requires-Python: >=3.9
Requires-Dist: structlog==24.2.0
